notelist/__init__.py
notelist/__main__.py
notelist/auth.py
notelist/cli.py
notelist/errors.py
notelist/responses.py
notelist/tools.py
notelist/config/__init__.py
notelist/config/settings.json
notelist/db/__init__.py
notelist/db/main/__init__.py
notelist/db/main/notebooks.py
notelist/db/main/notes.py
notelist/db/main/users.py
notelist/db/temp/__init__.py
notelist/db/temp/blocklist.py
notelist/schemas/__init__.py
notelist/schemas/auth.py
notelist/schemas/notebooks.py
notelist/schemas/notes.py
notelist/schemas/search.py
notelist/schemas/users.py
notelist/static/index.css
notelist/templates/auth.html
notelist/templates/index.html
notelist/templates/notebooks.html
notelist/templates/notes.html
notelist/templates/search.html
notelist/templates/users.html
notelist/views/__init__.py
notelist/views/authentication.py
notelist/views/notebooks.py
notelist/views/notes.py
notelist/views/search.py
notelist/views/users.py
notelist-0.10.0.dist-info/LICENSE
notelist-0.10.0.dist-info/METADATA
notelist-0.10.0.dist-info/WHEEL
notelist-0.10.0.dist-info/entry_points.txt
notelist-0.10.0.dist-info/top_level.txt
notelist-0.10.0.dist-info/RECORD
