Metadata-Version: 2.1
Name: notelist
Version: 0.10.0
Summary: Tag based note taking REST API
Home-page: https://github.com/jajimenez/notelist
Author: Jose A. Jimenez
Author-email: jajimenezcarm@gmail.com
License: MIT
Platform: UNKNOWN
Classifier: Programming Language :: Python :: 3
Classifier: Operating System :: OS Independent
Classifier: License :: OSI Approved :: MIT License
Requires-Python: >=3.9.0
Requires-Dist: Flask (==2.2.0)
Requires-Dist: Flask-JWT-Extended (==4.4.3)
Requires-Dist: marshmallow (==3.17.0)
Requires-Dist: pymongo (==4.2.0)
Requires-Dist: redis (==4.3.4)
